voidpop.py
voidpop-0.1.0.dist-info/LICENSE
voidpop-0.1.0.dist-info/METADATA
voidpop-0.1.0.dist-info/WHEEL
voidpop-0.1.0.dist-info/entry_points.txt
voidpop-0.1.0.dist-info/top_level.txt
voidpop-0.1.0.dist-info/RECORD
